tweets2pdf/__init__.py
tweets2pdf/__main__.py
tweets2pdf/pdf.py
tweets2pdf/settings.py
tweets2pdf/tweet.py
tweets2pdf/utils.py
tweets2pdf-0.0.5.dist-info/LICENSE
tweets2pdf-0.0.5.dist-info/METADATA
tweets2pdf-0.0.5.dist-info/WHEEL
tweets2pdf-0.0.5.dist-info/entry_points.txt
tweets2pdf-0.0.5.dist-info/top_level.txt
tweets2pdf-0.0.5.dist-info/RECORD
