Metadata-Version: 2.1
Name: tweets2pdf
Version: 0.0.5
Summary: Parse a Twitter achive JSON and produce a PDF file.
Project-URL: Homepage, https://github.com/qedjoe/tweet-parser
Project-URL: Bug Tracker, https://github.com/qedjoe/tweet-parser/issues
Classifier: Programming Language :: Python :: 3
Classifier: License :: OSI Approved :: MIT License
Classifier: Operating System :: OS Independent
Requires-Python: >=3.7
License-File: LICENSE
Requires-Dist: pytz
Requires-Dist: python-dateutil
Requires-Dist: fpdf
Requires-Dist: requests
Requires-Dist: emoji
